{"localities": ["Reedville, VT", "Chester, VT", "Baltimore, VT", "Simonsville, VT", "Brockways Mills, VT", "Andover, VT", "Athens, VT", "North Windham, VT", "Bartonsville, VT", "Peaseville, VT", "Middletown, VT"], "state": "VT", "postal_code": "05143", "locality": "Chester, VT", "lat": 43.27763, "region": {"fips": "50", "abbr": "VT", "name": "Vermont"}, "city": "Chester", "type": "STANDARD", "lng": -72.640348, "counties": [{"fips": "025", "name": "Windham County"}, {"fips": "027", "name": "Windsor County"}]}