{"localities": ["Benwood, IN", "Rocky Fork Lake, IN", "Bee Ridge, IN", "Art, IN", "Prairie City, IN", "Cloverland, IN", "Asherville, IN", "Cardonia, IN", "Turner, IN", "Brazil, IN", "Billtown, IN", "Lena, IN", "Billville, IN", "Alma Lake, IN", "Dick Johnson, IN", "Hoosierville, IN", "Wey Lake, IN", "Stearleyville, IN"], "state": "IN", "postal_code": "47834", "locality": "Brazil, IN", "lat": 39.525549, "region": {"fips": "18", "abbr": "IN", "name": "Indiana"}, "city": "Brazil", "type": "STANDARD", "lng": -87.121971, "counties": [{"fips": "021", "name": "Clay County"}, {"fips": "121", "name": "Parke County"}, {"fips": "133", "name": "Putnam County"}, {"fips": "167", "name": "Vigo County"}]}