{"localities": ["Parc Tiburon, PR", "Repto Las Llanadas, PR", "Urb Sol Naciente, PR", "Parc Garrochales, PR", "Parc Palenque, PR", "Est De Florida, PR", "Parc Imbery, PR", "Villas De La Sabana, PR", "Urb Las Praderas, PR", "Parc Punta Palmas, PR", "Brisas Del Monte, PR", "Villa Central, PR", "Urb Las Delicias, PR", "Ext Parc Punta Palmas, PR", "Urb Ortega, PR", "Villa Barcelona, PR", "Parc Magueyes, PR", "Brisas De Llanadas, PR", "Urb Cataluna, PR", "Barceloneta, PR", "Bda Catalana, PR", "Villa Georgetti, PR", "Urb Cimarrona Ct, PR", "Urb Plazuela Estates, PR", "Ext Est De Imbery, PR", "Est De Barceloneta, PR"], "state": "PR", "postal_code": "00617", "locality": "Barceloneta, PR", "lat": 18.445147, "region": {"fips": "72", "abbr": "PR", "name": "Puerto Rico"}, "city": "Barceloneta", "type": "STANDARD", "lng": -66.559696, "counties": [{"fips": "017", "name": "Barceloneta Municipio"}, {"fips": "054", "name": "Florida Municipio"}]}