{"localities": ["Red Cliff Indian Reservation, WI", "Stockbridge Indian Reservati, WI", "Ashland, WI", "Moquah, WI", "Sanborn, WI", "Potawatomi Indian Reservatio, WI", "Lac Courte Oreilles Indian R, WI", "Bad River Indian Reservation, WI", "Lac Du Flambeau Reservation, WI", "Oneida Indian Reservation, WI"], "state": "WI", "postal_code": "54806", "locality": "Ashland, WI", "lat": 46.552396, "region": {"fips": "55", "abbr": "WI", "name": "Wisconsin"}, "city": "Ashland", "type": "STANDARD", "lng": -90.870143, "counties": [{"fips": "003", "name": "Ashland County"}, {"fips": "007", "name": "Bayfield County"}]}